utils.py
beacon2_import/__init__.py
beacon2_import/beacon2_import.py
beacon2_import/utils.py
beacon2_search/__init__.py
beacon2_search/beacon2_search.py
beacon2_search/utils.py
search/__init__.py
search/beacon2_search.py
search/utils.py
beacon2_import-2.2.4.dist-info/METADATA
beacon2_import-2.2.4.dist-info/WHEEL
beacon2_import-2.2.4.dist-info/dependency_links.txt
beacon2_import-2.2.4.dist-info/entry_points.txt
beacon2_import-2.2.4.dist-info/top_level.txt
beacon2_import-2.2.4.dist-info/RECORD
