Metadata-Version: 2.1
Name: beacon2-import
Version: 2.2.4
Summary: Seamlessly import and query all of the beacon protocol collections
Author: Khaled Jumah
Author-email: khalled.jooma@yahoo.com
License: CC-BY-NC-4.0
Requires-Dist: jsonschema
Requires-Dist: dataclasses
Requires-Dist: bioblend
Requires-Dist: cyvcf2
Requires-Dist: pymongo
